{
  "scene_info": {
    "map_name": "SDBP_Map_009",
    "room_name": "livingRoom",
    "room_bound": {
      "x_min": 64.81600189208984,
      "y_min": -705.3319702148438,
      "z_min": 0.0,
      "x_max": 575.0989990234375,
      "y_max": -195.36099243164062,
      "z_max": 294.9549865722656
    },
    "table_id": "BP_CoffeeTable_Emotion_002_C_1",
    "base_id": "BP_CoffeeTable_Emotion_002",
    "position": {
      "x": 310.81201171875,
      "y": -428.0719299316406,
      "z": 1.5948238372802734
    },
    "rotation": {
      "x": 0.0,
      "y": -0.0,
      "z": 0.7071067690849304,
      "w": 0.7071067690849304
    },
    "aabb_bounds": {
      "min": {
        "x": 274.6624755859375,
        "y": -496.570556640625,
        "z": 17.556011199951172
      },
      "max": {
        "x": 346.58819580078125,
        "y": -359.61114501953125,
        "z": 46.629241943359375
      }
    }
  },
  "objects": [
    {
      "id": "BP_SofaStool_01_C_2147339594",
      "base_id": "BP_SofaStool_01",
      "type": "sofastool",
      "location": {
        "x": 331.0457458496094,
        "y": -554.9861450195312,
        "z": 0.0
      },
      "rotation": {
        "w": 0.9968580603599548,
        "x": 0.0061849863268435,
        "y": 0.0004899376071989536,
        "z": 0.07896512746810913
      },
      "entity_min": {
        "x": 302.3064270019531,
        "y": -601.8933715820312,
        "z": -0.45455610752105713
      },
      "entity_max": {
        "x": 362.3509216308594,
        "y": -524.4287109375,
        "z": 110.62369537353516
      },
      "entity_size": {
        "x": 1.0,
        "y": 1.0,
        "z": 1.0
      },
      "direction": "right",
      "is_sittable": true,
      "movable": true,
      "matched": false,
      "owner": "room"
    },
    {
      "id": "BP_SofaStool_01_C_2147339590",
      "base_id": "BP_SofaStool_01",
      "type": "sofastool",
      "location": {
        "x": 346.0357360839844,
        "y": -321.7058410644531,
        "z": 0.0
      },
      "rotation": {
        "w": -0.159210205078125,
        "x": -0.00113300746306777,
        "y": -0.0070254686288535595,
        "z": -0.9872190952301025
      },
      "entity_min": {
        "x": 304.2476806640625,
        "y": -334.2509460449219,
        "z": -0.530785858631134
      },
      "entity_max": {
        "x": 393.12786865234375,
        "y": -293.2718811035156,
        "z": 110.66956329345703
      },
      "entity_size": {
        "x": 1.0,
        "y": 1.0,
        "z": 1.0
      },
      "direction": "back",
      "is_sittable": true,
      "movable": true,
      "matched": false,
      "owner": "room"
    },
    {
      "id": "BP_SofaStool_01_C_2147339586",
      "base_id": "BP_SofaStool_01",
      "type": "sofastool",
      "location": {
        "x": 217.36294555664062,
        "y": -464.12469482421875,
        "z": 0.0
      },
      "rotation": {
        "w": 0.8245776295661926,
        "x": 0.006564196199178696,
        "y": -0.004503297619521618,
        "z": -0.5656928420066833
      },
      "entity_min": {
        "x": 165.49497985839844,
        "y": -488.5080871582031,
        "z": -0.6013548374176025
      },
      "entity_max": {
        "x": 253.4149169921875,
        "y": -445.79998779296875,
        "z": 110.7116928100586
      },
      "entity_size": {
        "x": 1.0,
        "y": 1.0,
        "z": 1.0
      },
      "direction": "front",
      "is_sittable": true,
      "movable": true,
      "matched": false,
      "owner": "room"
    },
    {
      "id": "BP_Phone_04_C_2147339384",
      "base_id": "BP_Phone_04",
      "my_type": "phone",
      "location": {
        "x": 280.6641540527344,
        "y": -418.09393310546875,
        "z": 46.43749237060547
      },
      "rotation": {
        "w": 0.38986191153526306,
        "x": 0.02625460736453533,
        "y": -0.011119985021650791,
        "z": -0.9204317927360535
      },
      "entity_min": {
        "x": 278.3369445800781,
        "y": -424.9853210449219,
        "z": 46.568153381347656
      },
      "entity_max": {
        "x": 282.9526062011719,
        "y": -411.202880859375,
        "z": 46.9796257019043
      },
      "entity_size": {
        "x": 1.0,
        "y": 1.0,
        "z": 1.0
      },
      "owner": "SDBP_Aich_Liqiuyue_C_2147461444",
      "grid_x": "-3",
      "grid_y": "1",
      "grid_id": "32",
      "chain_item_id": null
    },
    {
      "id": "BP_Toy_Car_C_2147339383",
      "base_id": "BP_Toy_Car",
      "my_type": "boytoy",
      "location": {
        "x": 320.6253662109375,
        "y": -448.0908508300781,
        "z": 46.73078918457031
      },
      "rotation": {
        "w": 0.10094624757766724,
        "x": -5.0633345381356776e-05,
        "y": -3.176302925567143e-05,
        "z": 0.994891881942749
      },
      "entity_min": {
        "x": 313.8260192871094,
        "y": -455.46044921875,
        "z": 46.630332946777344
      },
      "entity_max": {
        "x": 327.1509704589844,
        "y": -441.0106201171875,
        "z": 55.21657180786133
      },
      "entity_size": {
        "x": 0.75,
        "y": 0.75,
        "z": 0.75
      },
      "owner": "SDBP_Aich_AIBaby_Tiantian_90_C_2147461346",
      "grid_x": "1",
      "grid_y": "-2",
      "grid_id": "20",
      "chain_item_id": null
    },
    {
      "id": "BP_Drink_Sprite_01_C_2147339382",
      "base_id": "BP_Drink_Sprite_01",
      "my_type": "drink",
      "location": {
        "x": 300.6253356933594,
        "y": -418.0908508300781,
        "z": 46.62924575805664
      },
      "rotation": {
        "w": 0.9660953283309937,
        "x": -0.0,
        "y": 0.0,
        "z": -0.2581856846809387
      },
      "entity_min": {
        "x": 295.00469970703125,
        "y": -419.6376953125,
        "z": 46.62924575805664
      },
      "entity_max": {
        "x": 306.2459716796875,
        "y": -416.54400634765625,
        "z": 77.54827880859375
      },
      "entity_size": {
        "x": 0.20000000298023224,
        "y": 0.20000000298023224,
        "z": 0.20000000298023224
      },
      "owner": "SDBP_Aich_Liqiuyue_C_2147461444",
      "grid_x": "-1",
      "grid_y": "1",
      "grid_id": "8",
      "chain_item_id": null
    },
    {
      "id": "BP_Cup_Kitchen_003_C_2147339381",
      "base_id": "BP_Cup_Kitchen_003",
      "my_type": "bigcup",
      "location": {
        "x": 330.58172607421875,
        "y": -468.1113586425781,
        "z": 46.638370513916016
      },
      "rotation": {
        "w": 0.8252701163291931,
        "x": 3.804502313187186e-08,
        "y": -1.1295598056904055e-07,
        "z": -0.5647382140159607
      },
      "entity_min": {
        "x": 321.70751953125,
        "y": -470.1454162597656,
        "z": 46.629241943359375
      },
      "entity_max": {
        "x": 339.68951416015625,
        "y": -466.03564453125,
        "z": 55.35109329223633
      },
      "entity_size": {
        "x": 1.2000000476837158,
        "y": 1.2000000476837158,
        "z": 1.2000000476837158
      },
      "owner": "SDBP_Aich_AIBaby_Tiantian_90_C_2147461346",
      "grid_x": "2,3",
      "grid_y": "-4,-4",
      "grid_id": "64,78",
      "chain_item_id": null
    },
    {
      "id": "BP_Toy_Dog_C_2147339376",
      "base_id": "BP_Toy_Dog",
      "my_type": "toy",
      "location": {
        "x": 330.6253356933594,
        "y": -418.0908508300781,
        "z": 46.688323974609375
      },
      "rotation": {
        "w": 0.7781010270118713,
        "x": 0.0,
        "y": -0.0,
        "z": 0.6281391382217407
      },
      "entity_min": {
        "x": 324.0770568847656,
        "y": -428.389404296875,
        "z": 46.629241943359375
      },
      "entity_max": {
        "x": 337.1597900390625,
        "y": -407.7999267578125,
        "z": 68.26361083984375
      },
      "entity_size": {
        "x": 0.6000000238418579,
        "y": 0.6000000238418579,
        "z": 0.6000000238418579
      },
      "owner": "SDBP_Aich_AIBaby_Tiantian_90_C_2147461346",
      "grid_x": "2,2,2",
      "grid_y": "1,0,2",
      "grid_id": "17,12,29",
      "chain_item_id": null
    }
  ],
  "agents": [
    {
      "id": "SDBP_Aich_AIBaby_Tiantian_90_C_2147339579",
      "base_id": "SDBP_Aich_AIBaby_Tiantian_90",
      "type": "boy",
      "location": {
        "x": 252.94200134277344,
        "y": -395.3789978027344,
        "z": 78.79803466796875
      },
      "rotation": {
        "x": -0.0,
        "y": 0.0,
        "z": -0.382686048746109,
        "w": 0.9238784313201904
      },
      "entity_size": {
        "x": 1.0,
        "y": 1.0,
        "z": 1.0
      },
      "direction": "right",
      "status": "standing",
      "skeleton": {
        "spine_03": {
          "x": 253.5045,
          "y": -395.9959,
          "z": 59.546432
        },
        "clavicle_l": {
          "x": 249.47906,
          "y": -397.44455,
          "z": 71.52842
        },
        "pelvis": {
          "x": 252.477,
          "y": -394.95407,
          "z": 42.17229
        },
        "lowerarm_r": {
          "x": 261.05972,
          "y": -384.98618,
          "z": 55.257008
        },
        "ball_r": {
          "x": 257.62253,
          "y": -394.49783,
          "z": 2.4968
        },
        "head": {
          "x": 252.02847,
          "y": -394.51834,
          "z": 78.25915
        },
        "pinky_01_r": {
          "x": 263.4296,
          "y": -383.9017,
          "z": 39.81677
        },
        "foot_r": {
          "x": 252.38614,
          "y": -389.6004,
          "z": 4.1547422
        },
        "thumb_01_l": {
          "x": 243.53583,
          "y": -406.29245,
          "z": 45.236706
        },
        "hand_l": {
          "x": 241.7536,
          "y": -405.04926,
          "z": 45.835106
        },
        "calf_l": {
          "x": 247.85228,
          "y": -397.98703,
          "z": 22.944698
        },
        "thigh_l": {
          "x": 247.72955,
          "y": -400.88876,
          "z": 39.617664
        },
        "calf_r": {
          "x": 256.3209,
          "y": -391.33972,
          "z": 22.85831
        },
        "neck_01": {
          "x": 251.58382,
          "y": -394.06754,
          "z": 74.29604
        },
        "thumb_01_r": {
          "x": 263.81622,
          "y": -386.5315,
          "z": 44.913647
        },
        "pinky_01_l": {
          "x": 240.61649,
          "y": -405.87244,
          "z": 40.295574
        },
        "spine_02": {
          "x": 253.82742,
          "y": -396.30624,
          "z": 48.797302
        },
        "eye_jiont_r": {
          "x": 257.89102,
          "y": -396.3576,
          "z": 82.908195
        },
        "upperarm_r": {
          "x": 259.46262,
          "y": -386.61118,
          "z": 68.460106
        },
        "lowerarm_l": {
          "x": 240.93983,
          "y": -402.6537,
          "z": 55.44608
        },
        "ring_01_r": {
          "x": 264.28973,
          "y": -384.91,
          "z": 40.132843
        },
        "cc_base_r_eye": {
          "x": 257.89102,
          "y": -396.3576,
          "z": 82.908195
        },
        "eye_jiont_l": {
          "x": 253.74458,
          "y": -400.51797,
          "z": 82.93335
        },
        "cc_base_l_eye": {
          "x": 253.74458,
          "y": -400.51797,
          "z": 82.93335
        },
        "clavicle_r": {
          "x": 254.95872,
          "y": -391.966,
          "z": 71.51839
        },
        "foot_l": {
          "x": 247.2082,
          "y": -394.48474,
          "z": 4.076329
        },
        "ring_01_l": {
          "x": 241.57433,
          "y": -406.81158,
          "z": 40.58541
        },
        "index_01_l": {
          "x": 243.84549,
          "y": -408.33133,
          "z": 41.310936
        },
        "upperarm_l": {
          "x": 243.9904,
          "y": -401.80795,
          "z": 68.50174
        },
        "ball_l": {
          "x": 251.59741,
          "y": -400.19144,
          "z": 2.3859136
        },
        "thigh_r": {
          "x": 258.41577,
          "y": -390.21072,
          "z": 39.61564
        },
        "spine_01": {
          "x": 253.14513,
          "y": -395.62546,
          "z": 46.630775
        },
        "cc_base_pelvis": {
          "x": 252.477,
          "y": -394.95407,
          "z": 42.17194
        },
        "index_01_r": {
          "x": 265.63593,
          "y": -387.24115,
          "z": 40.941463
        },
        "middle_01_r": {
          "x": 265.08542,
          "y": -385.9062,
          "z": 40.41541
        },
        "middle_01_l": {
          "x": 242.52448,
          "y": -407.68506,
          "z": 40.838337
        },
        "hand_r": {
          "x": 262.74582,
          "y": -384.6235,
          "z": 45.439026
        }
      },
      "skeleton_bone_count": 37,
      "action_status": {
        "full_body_type": "STANDING",
        "upper_body_type": "BODY_IDLE",
        "left_hand_state_type": "HAND_IDLE",
        "right_hand_state_type": "HAND_IDLE",
        "head_state_type": "HEAD_IDLE",
        "current_speed": 0.0
      }
    },
    {
      "id": "SDBP_Aich_Liqiuyue_C_2147339478",
      "base_id": "SDBP_Aich_Liqiuyue",
      "type": "woman",
      "location": {
        "x": 375.44500732421875,
        "y": -450.7170104980469,
        "z": 82.1500015258789
      },
      "rotation": {
        "x": -0.0,
        "y": 0.0,
        "z": -0.9876895546913147,
        "w": 0.15642672777175903
      },
      "entity_size": {
        "x": 1.0,
        "y": 1.0,
        "z": 1.0
      },
      "direction": "left",
      "status": "standing",
      "skeleton": {
        "spine_03": {
          "x": 372.28195,
          "y": -454.02023,
          "z": 110.456085
        },
        "clavicle_l": {
          "x": 372.84323,
          "y": -448.81155,
          "z": 129.7148
        },
        "pelvis": {
          "x": 373.8255,
          "y": -453.52994,
          "z": 86.66729
        },
        "lowerarm_r": {
          "x": 384.15097,
          "y": -472.45575,
          "z": 101.71164
        },
        "ball_r": {
          "x": 373.2069,
          "y": -469.93747,
          "z": 3.398975
        },
        "head": {
          "x": 372.38742,
          "y": -454.20612,
          "z": 142.20996
        },
        "pinky_01_r": {
          "x": 379.9868,
          "y": -478.298,
          "z": 72.76095
        },
        "foot_r": {
          "x": 383.14612,
          "y": -461.34805,
          "z": 7.0732737
        },
        "thumb_01_l": {
          "x": 365.14767,
          "y": -431.6948,
          "z": 79.49374
        },
        "hand_l": {
          "x": 366.51215,
          "y": -429.80304,
          "z": 80.65915
        },
        "calf_l": {
          "x": 369.50305,
          "y": -442.41226,
          "z": 45.96581
        },
        "neck_01": {
          "x": 374.80734,
          "y": -453.4955,
          "z": 135.28462
        },
        "thigh_l": {
          "x": 372.7797,
          "y": -445.174,
          "z": 84.57193
        },
        "calf_r": {
          "x": 375.83398,
          "y": -464.197,
          "z": 45.637325
        },
        "thumb_01_r": {
          "x": 377.72473,
          "y": -476.05527,
          "z": 79.297646
        },
        "pinky_01_l": {
          "x": 365.21912,
          "y": -428.0942,
          "z": 73.176636
        },
        "spine_02": {
          "x": 372.44135,
          "y": -453.9248,
          "z": 97.46523
        },
        "upperarm_r": {
          "x": 380.15225,
          "y": -467.94968,
          "z": 125.45979
        },
        "eye_jiont_r": {
          "x": 367.24973,
          "y": -459.94736,
          "z": 148.023
        },
        "lowerarm_l": {
          "x": 372.01108,
          "y": -431.66818,
          "z": 102.04736
        },
        "ring_01_r": {
          "x": 378.32874,
          "y": -478.20966,
          "z": 73.07654
        },
        "cc_base_r_eye": {
          "x": 367.24973,
          "y": -459.94736,
          "z": 148.023
        },
        "eye_jiont_l": {
          "x": 365.07095,
          "y": -454.3029,
          "z": 148.64568
        },
        "cc_base_l_eye": {
          "x": 365.07095,
          "y": -454.3029,
          "z": 148.64568
        },
        "clavicle_r": {
          "x": 375.4981,
          "y": -458.4465,
          "z": 129.65057
        },
        "foot_l": {
          "x": 374.37076,
          "y": -439.45953,
          "z": 7.025161
        },
        "ring_01_l": {
          "x": 363.94412,
          "y": -429.1521,
          "z": 73.51083
        },
        "index_01_l": {
          "x": 361.79764,
          "y": -431.8897,
          "z": 73.98751
        },
        "upperarm_l": {
          "x": 371.86438,
          "y": -438.22446,
          "z": 125.65399
        },
        "ball_l": {
          "x": 361.2358,
          "y": -439.27805,
          "z": 3.353635
        },
        "thigh_r": {
          "x": 376.62686,
          "y": -461.41068,
          "z": 84.374695
        },
        "spine_01": {
          "x": 372.6364,
          "y": -453.8835,
          "z": 93.37039
        },
        "cc_base_pelvis": {
          "x": 373.8255,
          "y": -453.52994,
          "z": 86.66732
        },
        "index_01_r": {
          "x": 374.98294,
          "y": -477.2767,
          "z": 73.59067
        },
        "middle_01_r": {
          "x": 376.69778,
          "y": -478.04037,
          "z": 73.21869
        },
        "hand_r": {
          "x": 379.9138,
          "y": -476.9187,
          "z": 80.42071
        },
        "middle_01_l": {
          "x": 362.72525,
          "y": -430.2474,
          "z": 73.66393
        }
      },
      "skeleton_bone_count": 37,
      "action_status": {
        "full_body_type": "STANDING",
        "upper_body_type": "BODY_IDLE",
        "left_hand_state_type": "HAND_IDLE",
        "right_hand_state_type": "HAND_IDLE",
        "head_state_type": "HEAD_IDLE",
        "current_speed": 0.0
      }
    }
  ],
  "cameras": [
    {
      "id": "BP_CoffeeTable_Emotion_002_C_1_Camera_1",
      "type": "camera",
      "position": {
        "x": 383.488525390625,
        "y": -540.2614135742188,
        "z": 160.0
      },
      "rotation": {
        "x": -0.29165664315223694,
        "y": 0.15980637073516846,
        "z": 0.8270640969276428,
        "w": 0.4531702697277069
      }
    }
  ],
  "timestamps": {
    "start_time": "2026-01-13T19:54:40.602321",
    "end_time": null
  }
}